[
	{
		"question": "How long does it take to build a camper van?",
		"answer": "The build process typically takes 4-8 weeks, depending on the customization and features you choose.",
		"tags": ["build time", "camper van conversion", "customization"]
	},
	{
		"question": "Can I customize the interior layout?",
		"answer": "Yes! We offer fully customizable layouts to fit your travel and lifestyle needs, from sleeping areas to kitchen setups.",
		"tags": ["custom camper", "interior design", "van layout"]
	},
	{
		"question": "Is the camper van suitable for off-road travel?",
		"answer": "Absolutely! Our designs are built for Indonesian roads, ensuring durability for off-road and long-distance travel.",
		"tags": ["off-road", "4x4 camper", "travel durability"]
	},
	{
		"question": "What type of power system is included?",
		"answer": "Our camper vans come with solar-powered systems, battery storage, and charging options for a self-sufficient experience.",
		"tags": ["solar energy", "van power system", "off-grid travel"]
	},
	{
		"question": "Do you offer a warranty on your camper conversions?",
		"answer": "Yes, we provide a warranty on workmanship and materials to ensure quality and peace of mind.",
		"tags": ["warranty", "quality assurance", "after-sales service"]
	}
	]

